ethik/__init__.py
ethik/__version__.py
ethik/classification_explainer.py
ethik/datasets.py
ethik/explainer.py
ethik/image_classification_explainer.py
ethik/regression_explainer.py
ethik/utils.py
ethik/data/diabetes.csv
ethik/data/law_data.csv
ethik-0.0.2.dist-info/LICENSE
ethik-0.0.2.dist-info/METADATA
ethik-0.0.2.dist-info/WHEEL
ethik-0.0.2.dist-info/top_level.txt
ethik-0.0.2.dist-info/RECORD
