Metadata-Version: 2.1
Name: ethik
Version: 0.0.2
Summary: A toolbox for fair and explainable machine learning
Home-page: https://github.com/MaxHalford/ethik
Author: Max Halford, Vincent Lefoulon
Author-email: maxhalford25@gmail.com, vincent.lefoulon@free.fr
License: BSD-3
Platform: UNKNOWN
Classifier: License :: OSI Approved :: BSD License
Classifier: Programming Language :: Python
Classifier: Programming Language :: Python :: 3
Classifier: Programming Language :: Python :: 3.6
Classifier: Programming Language :: Python :: 3.7
Classifier: Programming Language :: Python :: Implementation :: CPython
Classifier: Programming Language :: Python :: Implementation :: PyPy
Requires-Python: >=3.6.0
Requires-Dist: colorlover (>=0.3.0)
Requires-Dist: joblib (>=0.13.2)
Requires-Dist: numpy (>=1.16.1)
Requires-Dist: pandas (>=0.24.0)
Requires-Dist: plotly (>=4.1.1)
Requires-Dist: scipy (>=1.3.0)
Requires-Dist: tqdm (>=4.36.1)
